topsis/__init__.py
topsis/topsis.py
topsis_decision_analysis-1.0.1.dist-info/licenses/LICENSE.txt
topsis_decision_analysis-1.0.1.dist-info/METADATA
topsis_decision_analysis-1.0.1.dist-info/WHEEL
topsis_decision_analysis-1.0.1.dist-info/entry_points.txt
topsis_decision_analysis-1.0.1.dist-info/top_level.txt
topsis_decision_analysis-1.0.1.dist-info/RECORD
