Metadata-Version: 2.4
Name: topsis-decision-analysis
Version: 1.0.1
Summary: A Python implementation of the TOPSIS method for multi-criteria decision making
Author: Sartaj Singh Virdi
Requires-Python: >=3.7
License-File: LICENSE.txt
Requires-Dist: pandas
Requires-Dist: numpy
Dynamic: author
Dynamic: description
Dynamic: description-content-type
Dynamic: license-file
Dynamic: requires-dist
Dynamic: requires-python
Dynamic: summary
